imppkg/harmonic_mean.cpython-39-x86_64-linux-gnu.so
imppkg/harmonic_mean.pyx
imppkg/harmonic_mean.c
imppkg/py.typed
imppkg/__init__.py
imppkg/harmony.py
imppkg/data.json
pubpypack_harmony_bill_melvin-0.0.4.dist-info/METADATA
pubpypack_harmony_bill_melvin-0.0.4.dist-info/LICENSE
pubpypack_harmony_bill_melvin-0.0.4.dist-info/top_level.txt
pubpypack_harmony_bill_melvin-0.0.4.dist-info/RECORD
pubpypack_harmony_bill_melvin-0.0.4.dist-info/entry_points.txt
pubpypack_harmony_bill_melvin-0.0.4.dist-info/WHEEL
